.gitignore
LICENSE.txt
MANIFEST.in
README.md
about.md
requirements.txt
setup.py
Orange3_Chemoinformatics.egg-info/PKG-INFO
Orange3_Chemoinformatics.egg-info/SOURCES.txt
Orange3_Chemoinformatics.egg-info/dependency_links.txt
Orange3_Chemoinformatics.egg-info/entry_points.txt
Orange3_Chemoinformatics.egg-info/namespace_packages.txt
Orange3_Chemoinformatics.egg-info/not-zip-safe
Orange3_Chemoinformatics.egg-info/requires.txt
Orange3_Chemoinformatics.egg-info/top_level.txt
doc/Makefile
doc/conf.py
doc/index.rst
doc/make.bat
doc/_build/html/.buildinfo
doc/_build/html/genindex.html
doc/_build/html/index.html
doc/_build/html/objects.inv
doc/_build/html/search.html
doc/_build/html/searchindex.js
doc/_build/html/_images/MoleculeViewer.png
doc/_build/html/_sources/index.rst.txt
doc/_build/html/_sources/widgets/moleculeviewer.rst.txt
doc/_build/html/_static/ajax-loader.gif
doc/_build/html/_static/basic.css
doc/_build/html/_static/comment-bright.png
doc/_build/html/_static/comment-close.png
doc/_build/html/_static/comment.png
doc/_build/html/_static/doctools.js
doc/_build/html/_static/down-pressed.png
doc/_build/html/_static/down.png
doc/_build/html/_static/file.png
doc/_build/html/_static/jquery-3.1.0.js
doc/_build/html/_static/jquery.js
doc/_build/html/_static/minus.png
doc/_build/html/_static/nature.css
doc/_build/html/_static/plus.png
doc/_build/html/_static/pygments.css
doc/_build/html/_static/searchtools.js
doc/_build/html/_static/underscore-1.3.1.js
doc/_build/html/_static/underscore.js
doc/_build/html/_static/up-pressed.png
doc/_build/html/_static/up.png
doc/_build/html/_static/websupport.js
doc/_build/html/widgets/moleculeviewer.html
doc/widgets/moleculeviewer.rst
doc/widgets/icons/MoleculeViewer.png
orangecontrib/__init__.py
orangecontrib/chem/__init__.py
orangecontrib/chem/http2_client.py
orangecontrib/chem/molecule_embedder.py
orangecontrib/chem/utils.py
orangecontrib/chem/hyper/__init__.py
orangecontrib/chem/hyper/stream.py
orangecontrib/chem/tests/__init__.py
orangecontrib/chem/tests/test_example.py
orangecontrib/chem/widgets/__init__.py
orangecontrib/chem/widgets/owmoleculeembedding.py
orangecontrib/chem/widgets/owmoleculeviewer.py
orangecontrib/chem/widgets/icons/MoleculeViewer.png
orangecontrib/chem/widgets/icons/MoleculeViewer.svg
orangecontrib/chem/widgets/icons/category.svg