Metadata-Version: 1.0
Name: Orange3-Chemoinformatics
Version: 0.1.0
Summary: Orange3 add-on for Chemoinformatics.
Home-page: http://orange.biolab.si/download
Author: Bioinformatics Laboratory, FRI UL
Author-email: contact@orange.biolab.si
License: GPL3+
Keywords: orange3 add-on,orange3-chem
Platform: UNKNOWN
